mc_nag/__init__.py
mc_nag/base_utils/__init__.py
mc_nag/base_utils/click_cli.py
mc_nag/base_utils/exceptions.py
mc_nag/base_utils/metaclasses.py
mc_nag/base_utils/parser.py
mc_nag/base_utils/printers.py
mc_nag/base_utils/rule_evaluator.py
mc_nag/base_utils/models/__init__.py
mc_nag/base_utils/models/rule.py
mc_nag/base_utils/models/rule_directory.py
mc_nag/base_utils/models/template.py
tests/base_utils/__init__.py
tests/base_utils/test_base_parser.py
tests/base_utils/test_base_rule.py
tests/base_utils/test_base_template.py
tests/base_utils/test_printers.py
tests/base_utils/test_rule_directory.py
tests/base_utils/test_rule_evaluator.py
tests/base_utils/test_utils.py
tests/rules/__init__.py
tests/rules/bad/__init__.py
tests/rules/bad/another_bad_rule.py
tests/rules/bad/bad_rule.py
tests/rules/custom/__init__.py
tests/rules/custom/custom_rule_for_option_testing.py
tests/rules/custom/duplicate_custom_rule_for_testing.py
tests/rules/standard/__init__.py
tests/rules/standard/duplicate_custom_rule_for_testing.py
tests/rules/standard/standard_rule.py
tests/rules/with_params/__init__.py
tests/rules/with_params/some_threshold_rule.py
mc_nag-0.0.7.dist-info/LICENSE
mc_nag-0.0.7.dist-info/METADATA
mc_nag-0.0.7.dist-info/WHEEL
mc_nag-0.0.7.dist-info/top_level.txt
mc_nag-0.0.7.dist-info/RECORD
