Metadata-Version: 2.1
Name: mc-nag
Version: 0.0.7
Summary: mc-nag multi-cloud static analysis tool
Home-page: https://github.com/stelligent/mc-nag
Author: Stelligent
Author-email: stelligent@stelligent.com
License: UNKNOWN
Platform: UNKNOWN
Requires-Python: >=3.7
Requires-Dist: jstyleson
Requires-Dist: setuptools
Requires-Dist: wheel
Requires-Dist: click
Requires-Dist: pytest
Requires-Dist: pytest-cov
Requires-Dist: coverage
Requires-Dist: pylint
Requires-Dist: flake8
Requires-Dist: flake8-docstrings
Requires-Dist: autopep8
Requires-Dist: pycodestyle
Requires-Dist: pyyaml
Requires-Dist: twine
Requires-Dist: tabulate (==0.8.7)
